govee_ble/__init__.py
govee_ble/parser.py
govee_ble/py.typed
govee_ble-1.0.0.dist-info/METADATA
govee_ble-1.0.0.dist-info/WHEEL
govee_ble-1.0.0.dist-info/licenses/LICENSE
govee_ble-1.0.0.dist-info/RECORD
