Metadata-Version: 2.4
Name: govee-ble
Version: 1.0.0
Summary: Manage Govee BLE devices
License-Expression: Apache-2.0
License-File: LICENSE
Author: J. Nick Koston
Author-email: nick@koston.org
Requires-Python: >=3.10
Classifier: Development Status :: 2 - Pre-Alpha
Classifier: Intended Audience :: Developers
Classifier: Natural Language :: English
Classifier: Operating System :: OS Independent
Classifier: Programming Language :: Python :: 3
Classifier: Programming Language :: Python :: 3.10
Classifier: Programming Language :: Python :: 3.11
Classifier: Programming Language :: Python :: 3.12
Classifier: Programming Language :: Python :: 3.13
Classifier: Programming Language :: Python :: 3.14
Classifier: Topic :: Software Development :: Libraries
Provides-Extra: docs
Requires-Dist: Sphinx (>=5,<9) ; extra == "docs"
Requires-Dist: bluetooth-data-tools (>=0.1.2)
Requires-Dist: bluetooth-sensor-state-data (>=1.5.0)
Requires-Dist: cryptography (>=42.0.0)
Requires-Dist: home-assistant-bluetooth (>=1.3.0)
Requires-Dist: myst-parser (>=0.18,<4.1) ; extra == "docs"
Requires-Dist: sensor-state-data (>=2.18.0)
Requires-Dist: sphinx-rtd-theme (>=1,<4) ; extra == "docs"
Project-URL: Bug Tracker, https://github.com/bluetooth-devices/govee-ble/issues
Project-URL: Changelog, https://github.com/bluetooth-devices/govee-ble/blob/main/CHANGELOG.md
Project-URL: Documentation, https://govee-ble.readthedocs.io
Project-URL: Repository, https://github.com/bluetooth-devices/govee-ble
